vonage_utils/__init__.py
vonage_utils/_version.py
vonage_utils/errors.py
vonage_utils/models.py
vonage_utils/types.py
vonage_utils/utils.py
vonage_utils-1.1.3.dist-info/METADATA
vonage_utils-1.1.3.dist-info/WHEEL
vonage_utils-1.1.3.dist-info/top_level.txt
vonage_utils-1.1.3.dist-info/RECORD
