Metadata-Version: 2.1
Name: vonage-utils
Version: 1.1.3
Summary: Utils package containing objects for use with Vonage APIs
Author-email: Vonage <devrel@vonage.com>
Project-URL: Homepage, https://github.com/Vonage/vonage-python-sdk
Classifier: Programming Language :: Python
Classifier: Programming Language :: Python :: 3
Classifier: Programming Language :: Python :: 3.8
Classifier: Programming Language :: Python :: 3.9
Classifier: Programming Language :: Python :: 3.10
Classifier: Programming Language :: Python :: 3.11
Classifier: Programming Language :: Python :: 3.12
Classifier: License :: OSI Approved :: Apache Software License
Requires-Python: >=3.8
Requires-Dist: typing-extensions>=4.9.0
Requires-Dist: pydantic>=2.7.1
